{
    "token": "",
    "chat_id": "",

    "width": "1000",
    "height": "1000",

    "use_config_args": true,
    "args": {
        "--reproduce-chance": {
            "value": 0.5,
            "start": null,
            "end": null
        },

        "--min-percent": {
            "value": 0.5,
            "start": null,
            "end": null
        },
        "--max-percent": {
            "value": null,
            "start": null,
            "end": null
        },

        "--max-count": null,
        "--colors-number": null,
        "--color-background": null,

        "--opaque": {
            "value": false,
            "random": false
        },
        "--random-colors": {
            "value": true,
            "random": false
        },
        "--fade-in": {
            "value": false,
            "random": false
        },
        "--quadratic": {
            "value": false,
            "random": false
        }
    }
}
